llama_index/readers/airbyte_zendesk_support/__init__.py
llama_index/readers/airbyte_zendesk_support/base.py
llama_index_readers_airbyte_zendesk_support-0.4.1.dist-info/METADATA
llama_index_readers_airbyte_zendesk_support-0.4.1.dist-info/WHEEL
llama_index_readers_airbyte_zendesk_support-0.4.1.dist-info/licenses/LICENSE
llama_index_readers_airbyte_zendesk_support-0.4.1.dist-info/RECORD
